baycompx/__init__.py
baycompx/py.typed
baycompx/dists/__init__.py
baycompx/dists/normal.py
baycompx-0.1.0.dist-info/METADATA
baycompx-0.1.0.dist-info/WHEEL
baycompx-0.1.0.dist-info/RECORD
