Metadata-Version: 2.4
Name: baycompx
Version: 0.1.0
Summary: A personal library for Bayesian computation
Requires-Python: >=3.12
